{
    "classification": "category",
    "type": "electronic",
    "size": "ic",
    "color": "lga_12_pin_2_mm_x_2_mm",
    "description_main": "",
    "description_extra": "",
    "manufacturer": "",
    "part_number": "",
    "from_yaml": false,
    "make_files": true,
    "filter": "",
    "part_number_exact": "",
    "description": "category_electronic",
    "short_name": "Categoryelectronic",
    "classification_upper": "CATEGORY",
    "classification_capital": "Category",
    "classification_first_letter": "c",
    "classification_first_letter_upper": "C",
    "type_upper": "ELECTRONIC",
    "type_capital": "Electronic",
    "type_first_letter": "e",
    "type_first_letter_upper": "E",
    "size_upper": "IC",
    "size_capital": "Ic",
    "size_first_letter": "i",
    "size_first_letter_upper": "I",
    "color_upper": "LGA_12_PIN_2_MM_X_2_MM",
    "color_capital": "Lga 12 Pin 2 mm x 2 mm",
    "color_first_letter": "l",
    "color_first_letter_upper": "L",
    "description_main_upper": "",
    "description_main_capital": "",
    "description_main_first_letter": "",
    "description_main_first_letter_upper": "",
    "description_extra_upper": "",
    "description_extra_capital": "",
    "description_extra_first_letter": "",
    "description_extra_first_letter_upper": "",
    "manufacturer_upper": "",
    "manufacturer_capital": "",
    "manufacturer_first_letter": "",
    "manufacturer_first_letter_upper": "",
    "part_number_upper": "",
    "part_number_capital": "",
    "part_number_first_letter": "",
    "part_number_first_letter_upper": "",
    "id": "category_electronic_ic_lga_12_pin_2_mm_x_2_mm",
    "id_no_class": "electronic_ic_lga_12_pin_2_mm_x_2_mm",
    "id_no_type": "ic_lga_12_pin_2_mm_x_2_mm",
    "id_no_size": "lga_12_pin_2_mm_x_2_mm",
    "oomp_key": "oomp_category_electronic_ic_lga_12_pin_2_mm_x_2_mm",
    "github_link": "https://github.com/oomlout/oomlout_oomp_current_version_messy/tree/main/parts/category_electronic_ic_lga_12_pin_2_mm_x_2_mm",
    "link_main": "https://github.com/oomlout/oomlout_oomp_current_version_messy/tree/main/parts/category_electronic_ic_lga_12_pin_2_mm_x_2_mm",
    "directory": "parts/category_electronic_ic_lga_12_pin_2_mm_x_2_mm",
    "name": "Category Electronic Ic Lga 12 Pin 2 Mm X 2 Mm",
    "name_no_class": "Electronic Ic Lga 12 Pin 2 Mm X 2 Mm",
    "name_no_type": "Ic Lga 12 Pin 2 Mm X 2 Mm",
    "name_no_size": "Lga 12 Pin 2 Mm X 2 Mm",
    "short_code": "",
    "short_code_upper": "",
    "distributors": [],
    "manufacturers": [],
    "md5": "734b0f93c7cd45e2ea6057cc43ad46af",
    "md5_5": "734b0",
    "md5_5_upper": "734B0",
    "md5_6": "734b0f",
    "md5_6_upper": "734B0F",
    "md5_6_alpha": "4hy4v",
    "md5_6_alpha_upper": "4HY4V",
    "md5_10": "734b0f93c7",
    "md5_10_upper": "734B0F93C7",
    "oomp_word": "flags penguin sparkles",
    "oomp_word_list": [
        "flags",
        "penguin",
        "sparkles"
    ],
    "oomp_word_emoji": ":flags: :penguin: :sparkles:",
    "oomp_word_emoji_list": [
        ":flags:",
        ":penguin:",
        ":sparkles:"
    ],
    "size_only_numbers": "",
    "size_only_numbers_no_zeros": "",
    "description_only_numbers": "",
    "description_only_numbers_short": " ",
    "name_no_size_short": "Lga 12 Pin 2 Mm X 2 Mm",
    "description_or_color": "L ",
    "description_or_color_upper": "L ",
    "markdown_full": "[category_electronic_ic_lga_12_pin_2_mm_x_2_mm](https://github.com/oomlout/oomlout_oomp_current_version_messy/tree/main/parts/category_electronic_ic_lga_12_pin_2_mm_x_2_mm)<br>[](https://github.com/oomlout/oomlout_oomp_current_version_messy/tree/main/parts/category_electronic_ic_lga_12_pin_2_mm_x_2_mm)<br>[Category Electronic Ic Lga 12 Pin 2 Mm X 2 Mm](https://github.com/oomlout/oomlout_oomp_current_version_messy/tree/main/parts/category_electronic_ic_lga_12_pin_2_mm_x_2_mm)<br><br>",
    "markdown_short": "[category_electronic_ic_lga_12_pin_2_mm_x_2_mm](https://github.com/oomlout/oomlout_oomp_current_version_messy/tree/main/parts/category_electronic_ic_lga_12_pin_2_mm_x_2_mm)<br><br>"
}