{
    "classification": "oobb",
    "type": "part",
    "size": "tray_vertical",
    "color": "",
    "description_main": "13_01_60",
    "description_extra": "",
    "manufacturer": "",
    "part_number": "",
    "make_files": true,
    "short_name": "",
    "distributors": [],
    "classification_upper": "OOBB",
    "classification_capital": "Oobb",
    "classification_first_letter": "o",
    "classification_first_letter_upper": "O",
    "type_upper": "PART",
    "type_capital": "Part",
    "type_first_letter": "p",
    "type_first_letter_upper": "P",
    "size_upper": "TRAY_VERTICAL",
    "size_capital": "Tray Vertical",
    "size_first_letter": "t",
    "size_first_letter_upper": "T",
    "color_upper": "",
    "color_capital": "",
    "color_first_letter": "",
    "color_first_letter_upper": "",
    "description_main_upper": "13_01_60",
    "description_main_capital": "13 01.60",
    "description_main_first_letter": "1",
    "description_main_first_letter_upper": "1",
    "description_extra_upper": "",
    "description_extra_capital": "",
    "description_extra_first_letter": "",
    "description_extra_first_letter_upper": "",
    "manufacturer_upper": "",
    "manufacturer_capital": "",
    "manufacturer_first_letter": "",
    "manufacturer_first_letter_upper": "",
    "part_number_upper": "",
    "part_number_capital": "",
    "part_number_first_letter": "",
    "part_number_first_letter_upper": "",
    "id": "oobb_part_tray_vertical_13_01_60",
    "id_no_class": "part_tray_vertical_13_01_60",
    "id_no_type": "tray_vertical_13_01_60",
    "id_no_size": "13_01_60",
    "oomp_key": "oomp_oobb_part_tray_vertical_13_01_60",
    "github_link": "https://github.com/oomlout/oomlout_oomp_current_version_messy/tree/main/parts/oobb_part_tray_vertical_13_01_60",
    "link_main": "https://github.com/oomlout/oomlout_oomp_current_version_messy/tree/main/parts/oobb_part_tray_vertical_13_01_60",
    "directory": "parts/oobb_part_tray_vertical_13_01_60",
    "name": "Oobb Part Tray Vertical 13 01 60",
    "name_no_class": "Part Tray Vertical 13 01 60",
    "name_no_type": "Tray Vertical 13 01 60",
    "name_no_size": "13 01 60",
    "short_code": "",
    "short_code_upper": "",
    "manufacturers": [],
    "md5": "01784936eca8dda763ccb10fd57b57a5",
    "md5_5": "01784",
    "md5_5_upper": "01784",
    "md5_6": "017849",
    "md5_6_upper": "017849",
    "md5_6_alpha": "22bt",
    "md5_6_alpha_upper": "22BT",
    "md5_10": "01784936ec",
    "md5_10_upper": "01784936EC",
    "oomp_word": "smile bell hatching_chick",
    "oomp_word_list": [
        "smile",
        "bell",
        "hatching_chick"
    ],
    "oomp_word_emoji": ":smile: :bell: :hatching_chick:",
    "oomp_word_emoji_list": [
        ":smile:",
        ":bell:",
        ":hatching_chick:"
    ],
    "size_only_numbers": "",
    "size_only_numbers_no_zeros": "",
    "description_only_numbers": "130160",
    "description_only_numbers_short": "130k",
    "name_no_size_short": "13 01 60",
    "description_or_color": "130k",
    "description_or_color_upper": "130K",
    "markdown_full": "[oobb_part_tray_vertical_13_01_60](https://github.com/oomlout/oomlout_oomp_current_version_messy/tree/main/parts/oobb_part_tray_vertical_13_01_60)<br>[](https://github.com/oomlout/oomlout_oomp_current_version_messy/tree/main/parts/oobb_part_tray_vertical_13_01_60)<br>[Oobb Part Tray Vertical 13 01 60](https://github.com/oomlout/oomlout_oomp_current_version_messy/tree/main/parts/oobb_part_tray_vertical_13_01_60)<br><br>",
    "markdown_short": "[oobb_part_tray_vertical_13_01_60](https://github.com/oomlout/oomlout_oomp_current_version_messy/tree/main/parts/oobb_part_tray_vertical_13_01_60)<br><br>"
}