{
    "classification": "category",
    "type": "oobb",
    "size": "part",
    "color": "tray",
    "description_main": "",
    "description_extra": "tote",
    "manufacturer": "",
    "part_number": "",
    "from_yaml": false,
    "make_files": true,
    "filter": "",
    "part_number_exact": "",
    "description": "category_oobb",
    "short_name": "Categoryoobb",
    "classification_upper": "CATEGORY",
    "classification_capital": "Category",
    "classification_first_letter": "c",
    "classification_first_letter_upper": "C",
    "type_upper": "OOBB",
    "type_capital": "Oobb",
    "type_first_letter": "o",
    "type_first_letter_upper": "O",
    "size_upper": "PART",
    "size_capital": "Part",
    "size_first_letter": "p",
    "size_first_letter_upper": "P",
    "color_upper": "TRAY",
    "color_capital": "Tray",
    "color_first_letter": "t",
    "color_first_letter_upper": "T",
    "description_main_upper": "",
    "description_main_capital": "",
    "description_main_first_letter": "",
    "description_main_first_letter_upper": "",
    "description_extra_upper": "TOTE",
    "description_extra_capital": "Tote",
    "description_extra_first_letter": "t",
    "description_extra_first_letter_upper": "T",
    "manufacturer_upper": "",
    "manufacturer_capital": "",
    "manufacturer_first_letter": "",
    "manufacturer_first_letter_upper": "",
    "part_number_upper": "",
    "part_number_capital": "",
    "part_number_first_letter": "",
    "part_number_first_letter_upper": "",
    "id": "category_oobb_part_tray_tote",
    "id_no_class": "oobb_part_tray_tote",
    "id_no_type": "part_tray_tote",
    "id_no_size": "tray_tote",
    "oomp_key": "oomp_category_oobb_part_tray_tote",
    "link_github": "https://github.com/oomlout/oomlout_oomp_version_1_messy/tree/main/parts/category_oobb_part_tray_tote",
    "link_main": "https://github.com/oomlout/oomlout_oomp_version_1_messy/tree/main/parts/category_oobb_part_tray_tote",
    "link_redirect": "https://github.com/oomlout/oomlout_oomp_version_1_messy/tree/main/parts/category_oobb_part_tray_tote",
    "directory": "parts/category_oobb_part_tray_tote",
    "name": "Category Oobb Part Tray Tote",
    "name_no_class": "Oobb Part Tray Tote",
    "name_no_type": "Part Tray Tote",
    "name_no_size": "Tray Tote",
    "short_code": "",
    "short_code_upper": "",
    "distributors": [],
    "manufacturers": [],
    "md5": "ce1a3de86f02ba51a674be975a2d9764",
    "md5_5": "ce1a3",
    "md5_5_upper": "CE1A3",
    "md5_6": "ce1a3d",
    "md5_6_upper": "CE1A3D",
    "md5_6_alpha": "81i65",
    "md5_6_alpha_upper": "81I65",
    "md5_10": "ce1a3de86f",
    "md5_10_upper": "CE1A3DE86F",
    "oomp_word": "peach clap cow",
    "oomp_word_list": [
        "peach",
        "clap",
        "cow"
    ],
    "oomp_word_emoji": ":peach: :clap: :cow:",
    "oomp_word_emoji_list": [
        ":peach:",
        ":clap:",
        ":cow:"
    ],
    "size_only_numbers": "",
    "size_only_numbers_no_zeros": "",
    "description_only_numbers": "",
    "description_only_numbers_short": " ",
    "name_no_size_short": "Tray Tote",
    "description_or_color": "T ",
    "description_or_color_upper": "T ",
    "markdown_full": "[category_oobb_part_tray_tote](none)<br>[](none)<br>[Category Oobb Part Tray Tote](none)<br><br>",
    "markdown_short": "[category_oobb_part_tray_tote](none)<br><br>"
}