{
    "classification": "category",
    "type": "dish",
    "size": "",
    "color": "ikea_oftast",
    "description_main": "",
    "description_extra": "",
    "manufacturer": "",
    "part_number": "",
    "from_yaml": false,
    "make_files": true,
    "filter": "",
    "part_number_exact": "",
    "description": "category_dish",
    "short_name": "Categorydish",
    "classification_upper": "CATEGORY",
    "classification_capital": "Category",
    "classification_first_letter": "c",
    "classification_first_letter_upper": "C",
    "type_upper": "DISH",
    "type_capital": "Dish",
    "type_first_letter": "d",
    "type_first_letter_upper": "D",
    "size_upper": "",
    "size_capital": "",
    "size_first_letter": "",
    "size_first_letter_upper": "",
    "color_upper": "IKEA_OFTAST",
    "color_capital": "Ikea Oftast",
    "color_first_letter": "i",
    "color_first_letter_upper": "I",
    "description_main_upper": "",
    "description_main_capital": "",
    "description_main_first_letter": "",
    "description_main_first_letter_upper": "",
    "description_extra_upper": "",
    "description_extra_capital": "",
    "description_extra_first_letter": "",
    "description_extra_first_letter_upper": "",
    "manufacturer_upper": "",
    "manufacturer_capital": "",
    "manufacturer_first_letter": "",
    "manufacturer_first_letter_upper": "",
    "part_number_upper": "",
    "part_number_capital": "",
    "part_number_first_letter": "",
    "part_number_first_letter_upper": "",
    "id": "category_dish_ikea_oftast",
    "id_no_class": "dish_ikea_oftast",
    "id_no_type": "ikea_oftast",
    "id_no_size": "ikeaoftast",
    "oomp_key": "oomp_category_dish_ikea_oftast",
    "link_github": "https://github.com/oomlout/oomlout_oomp_version_1_messy/tree/main/parts/category_dish_ikea_oftast",
    "link_main": "https://github.com/oomlout/oomlout_oomp_version_1_messy/tree/main/parts/category_dish_ikea_oftast",
    "link_redirect": "https://github.com/oomlout/oomlout_oomp_version_1_messy/tree/main/parts/category_dish_ikea_oftast",
    "directory": "parts/category_dish_ikea_oftast",
    "name": "Category Dish Ikea Oftast",
    "name_no_class": "Dish Ikea Oftast",
    "name_no_type": "Ikea Oftast",
    "name_no_size": "Ikeaoftast",
    "short_code": "",
    "short_code_upper": "",
    "distributors": [],
    "manufacturers": [],
    "md5": "b6a66871575f5e8fa39235f05b5d3e8f",
    "md5_5": "b6a66",
    "md5_5_upper": "B6A66",
    "md5_6": "b6a668",
    "md5_6_upper": "B6A668",
    "md5_6_alpha": "74k88",
    "md5_6_alpha_upper": "74K88",
    "md5_10": "b6a6687157",
    "md5_10_upper": "B6A6687157",
    "oomp_word": "beer trumpet mushroom",
    "oomp_word_list": [
        "beer",
        "trumpet",
        "mushroom"
    ],
    "oomp_word_emoji": ":beer: :trumpet: :mushroom:",
    "oomp_word_emoji_list": [
        ":beer:",
        ":trumpet:",
        ":mushroom:"
    ],
    "size_only_numbers": "",
    "size_only_numbers_no_zeros": "",
    "description_only_numbers": "",
    "description_only_numbers_short": " ",
    "name_no_size_short": "Ikeaoftast",
    "description_or_color": "I ",
    "description_or_color_upper": "I ",
    "markdown_full": "[category_dish_ikea_oftast](none)<br>[](none)<br>[Category Dish Ikea Oftast](none)<br><br>",
    "markdown_short": "[category_dish_ikea_oftast](none)<br><br>"
}