{
    "classification": "category",
    "type": "tool",
    "size": "water_chiller",
    "color": "",
    "description_main": "",
    "description_extra": "tote",
    "manufacturer": "",
    "part_number": "",
    "from_yaml": false,
    "make_files": true,
    "filter": "",
    "part_number_exact": "",
    "description": "category_tool",
    "short_name": "Categorytool",
    "classification_upper": "CATEGORY",
    "classification_capital": "Category",
    "classification_first_letter": "c",
    "classification_first_letter_upper": "C",
    "type_upper": "TOOL",
    "type_capital": "Tool",
    "type_first_letter": "t",
    "type_first_letter_upper": "T",
    "size_upper": "WATER_CHILLER",
    "size_capital": "Water Chiller",
    "size_first_letter": "w",
    "size_first_letter_upper": "W",
    "color_upper": "",
    "color_capital": "",
    "color_first_letter": "",
    "color_first_letter_upper": "",
    "description_main_upper": "",
    "description_main_capital": "",
    "description_main_first_letter": "",
    "description_main_first_letter_upper": "",
    "description_extra_upper": "TOTE",
    "description_extra_capital": "Tote",
    "description_extra_first_letter": "t",
    "description_extra_first_letter_upper": "T",
    "manufacturer_upper": "",
    "manufacturer_capital": "",
    "manufacturer_first_letter": "",
    "manufacturer_first_letter_upper": "",
    "part_number_upper": "",
    "part_number_capital": "",
    "part_number_first_letter": "",
    "part_number_first_letter_upper": "",
    "id": "category_tool_water_chiller_tote",
    "id_no_class": "tool_water_chiller_tote",
    "id_no_type": "water_chiller_tote",
    "id_no_size": "tote",
    "oomp_key": "oomp_category_tool_water_chiller_tote",
    "github_link": "https://github.com/oomlout/oomlout_oomp_current_version_messy/tree/main/parts/category_tool_water_chiller_tote",
    "link_main": "https://github.com/oomlout/oomlout_oomp_current_version_messy/tree/main/parts/category_tool_water_chiller_tote",
    "directory": "parts/category_tool_water_chiller_tote",
    "name": "Category Tool Water Chiller Tote",
    "name_no_class": "Tool Water Chiller Tote",
    "name_no_type": "Water Chiller Tote",
    "name_no_size": "Tote",
    "short_code": "",
    "short_code_upper": "",
    "distributors": [],
    "manufacturers": [],
    "md5": "408afb3abd6e50ca0ec5e78f286623a9",
    "md5_5": "408af",
    "md5_5_upper": "408AF",
    "md5_6": "408afb",
    "md5_6_upper": "408AFB",
    "md5_6_alpha": "2insr",
    "md5_6_alpha_upper": "2INSR",
    "md5_10": "408afb3abd",
    "md5_10_upper": "408AFB3ABD",
    "oomp_word": "racehorse envelope ok",
    "oomp_word_list": [
        "racehorse",
        "envelope",
        "ok"
    ],
    "oomp_word_emoji": ":racehorse: :envelope: :ok:",
    "oomp_word_emoji_list": [
        ":racehorse:",
        ":envelope:",
        ":ok:"
    ],
    "size_only_numbers": "",
    "size_only_numbers_no_zeros": "",
    "description_only_numbers": "",
    "description_only_numbers_short": " ",
    "name_no_size_short": "Tote",
    "description_or_color": " ",
    "description_or_color_upper": " ",
    "markdown_full": "[category_tool_water_chiller_tote](https://github.com/oomlout/oomlout_oomp_current_version_messy/tree/main/parts/category_tool_water_chiller_tote)<br>[](https://github.com/oomlout/oomlout_oomp_current_version_messy/tree/main/parts/category_tool_water_chiller_tote)<br>[Category Tool Water Chiller Tote](https://github.com/oomlout/oomlout_oomp_current_version_messy/tree/main/parts/category_tool_water_chiller_tote)<br><br>",
    "markdown_short": "[category_tool_water_chiller_tote](https://github.com/oomlout/oomlout_oomp_current_version_messy/tree/main/parts/category_tool_water_chiller_tote)<br><br>"
}