{
    "classification": "oobb",
    "type": "part",
    "size": "tray",
    "color": "",
    "description_main": "08_13_21",
    "description_extra": "",
    "manufacturer": "",
    "part_number": "",
    "make_files": true,
    "short_name": "",
    "distributors": [],
    "classification_upper": "OOBB",
    "classification_capital": "Oobb",
    "classification_first_letter": "o",
    "classification_first_letter_upper": "O",
    "type_upper": "PART",
    "type_capital": "Part",
    "type_first_letter": "p",
    "type_first_letter_upper": "P",
    "size_upper": "TRAY",
    "size_capital": "Tray",
    "size_first_letter": "t",
    "size_first_letter_upper": "T",
    "color_upper": "",
    "color_capital": "",
    "color_first_letter": "",
    "color_first_letter_upper": "",
    "description_main_upper": "08_13_21",
    "description_main_capital": "08.13.21",
    "description_main_first_letter": "0",
    "description_main_first_letter_upper": "0",
    "description_extra_upper": "",
    "description_extra_capital": "",
    "description_extra_first_letter": "",
    "description_extra_first_letter_upper": "",
    "manufacturer_upper": "",
    "manufacturer_capital": "",
    "manufacturer_first_letter": "",
    "manufacturer_first_letter_upper": "",
    "part_number_upper": "",
    "part_number_capital": "",
    "part_number_first_letter": "",
    "part_number_first_letter_upper": "",
    "id": "oobb_part_tray_08_13_21",
    "id_no_class": "part_tray_08_13_21",
    "id_no_type": "tray_08_13_21",
    "id_no_size": "08_13_21",
    "oomp_key": "oomp_oobb_part_tray_08_13_21",
    "github_link": "https://github.com/oomlout/oomlout_oomp_current_version_messy/tree/main/parts/oobb_part_tray_08_13_21",
    "link_main": "https://github.com/oomlout/oomlout_oomp_current_version_messy/tree/main/parts/oobb_part_tray_08_13_21",
    "directory": "parts/oobb_part_tray_08_13_21",
    "name": "Oobb Part Tray 08 13 21",
    "name_no_class": "Part Tray 08 13 21",
    "name_no_type": "Tray 08 13 21",
    "name_no_size": "08 13 21",
    "short_code": "",
    "short_code_upper": "",
    "manufacturers": [],
    "md5": "b8ef18eea6ce338a2525514a60a8d15b",
    "md5_5": "b8ef1",
    "md5_5_upper": "B8EF1",
    "md5_6": "b8ef18",
    "md5_6_upper": "B8EF18",
    "md5_6_alpha": "77rq0",
    "md5_6_alpha_upper": "77RQ0",
    "md5_10": "b8ef18eea6",
    "md5_10_upper": "B8EF18EEA6",
    "oomp_word": "hamburger truck hand",
    "oomp_word_list": [
        "hamburger",
        "truck",
        "hand"
    ],
    "oomp_word_emoji": ":hamburger: :truck: :hand:",
    "oomp_word_emoji_list": [
        ":hamburger:",
        ":truck:",
        ":hand:"
    ],
    "size_only_numbers": "",
    "size_only_numbers_no_zeros": "",
    "description_only_numbers": "081321",
    "description_only_numbers_short": "81k",
    "name_no_size_short": "08 13 21",
    "description_or_color": "81k",
    "description_or_color_upper": "81K",
    "markdown_full": "[oobb_part_tray_08_13_21](https://github.com/oomlout/oomlout_oomp_current_version_messy/tree/main/parts/oobb_part_tray_08_13_21)<br>[](https://github.com/oomlout/oomlout_oomp_current_version_messy/tree/main/parts/oobb_part_tray_08_13_21)<br>[Oobb Part Tray 08 13 21](https://github.com/oomlout/oomlout_oomp_current_version_messy/tree/main/parts/oobb_part_tray_08_13_21)<br><br>",
    "markdown_short": "[oobb_part_tray_08_13_21](https://github.com/oomlout/oomlout_oomp_current_version_messy/tree/main/parts/oobb_part_tray_08_13_21)<br><br>"
}