{
    "classification": "category",
    "type": "warehouse",
    "size": "",
    "color": "",
    "description_main": "",
    "description_extra": "",
    "manufacturer": "",
    "part_number": "",
    "from_yaml": false,
    "make_files": true,
    "filter": "",
    "part_number_exact": "",
    "description": "category_warehouse",
    "short_name": "Categorywarehouse",
    "classification_upper": "CATEGORY",
    "classification_capital": "Category",
    "classification_first_letter": "c",
    "classification_first_letter_upper": "C",
    "type_upper": "WAREHOUSE",
    "type_capital": "Warehouse",
    "type_first_letter": "w",
    "type_first_letter_upper": "W",
    "size_upper": "",
    "size_capital": "",
    "size_first_letter": "",
    "size_first_letter_upper": "",
    "color_upper": "",
    "color_capital": "",
    "color_first_letter": "",
    "color_first_letter_upper": "",
    "description_main_upper": "",
    "description_main_capital": "",
    "description_main_first_letter": "",
    "description_main_first_letter_upper": "",
    "description_extra_upper": "",
    "description_extra_capital": "",
    "description_extra_first_letter": "",
    "description_extra_first_letter_upper": "",
    "manufacturer_upper": "",
    "manufacturer_capital": "",
    "manufacturer_first_letter": "",
    "manufacturer_first_letter_upper": "",
    "part_number_upper": "",
    "part_number_capital": "",
    "part_number_first_letter": "",
    "part_number_first_letter_upper": "",
    "id": "category_warehouse",
    "id_no_class": "warehouse",
    "id_no_type": "warehouse",
    "id_no_size": "warehouse",
    "oomp_key": "oomp_category_warehouse",
    "github_link": "https://github.com/oomlout/oomlout_oomp_current_version_messy/tree/main/parts/category_warehouse",
    "link_main": "https://github.com/oomlout/oomlout_oomp_current_version_messy/tree/main/parts/category_warehouse",
    "directory": "parts/category_warehouse",
    "name": "Category Warehouse",
    "name_no_class": "Warehouse",
    "name_no_type": "Warehouse",
    "name_no_size": "Warehouse",
    "short_code": "",
    "short_code_upper": "",
    "distributors": [],
    "manufacturers": [],
    "md5": "c1b51a73b7b1ad44ea3dabff169b2c4a",
    "md5_5": "c1b51",
    "md5_5_upper": "C1B51",
    "md5_6": "c1b51a",
    "md5_6_upper": "C1B51A",
    "md5_6_alpha": "7k3dm",
    "md5_6_alpha_upper": "7K3DM",
    "md5_10": "c1b51a73b7",
    "md5_10_upper": "C1B51A73B7",
    "oomp_word": "doughnut tea clap",
    "oomp_word_list": [
        "doughnut",
        "tea",
        "clap"
    ],
    "oomp_word_emoji": ":doughnut: :tea: :clap:",
    "oomp_word_emoji_list": [
        ":doughnut:",
        ":tea:",
        ":clap:"
    ],
    "size_only_numbers": "",
    "size_only_numbers_no_zeros": "",
    "description_only_numbers": "",
    "description_only_numbers_short": " ",
    "name_no_size_short": "Warehouse",
    "description_or_color": " ",
    "description_or_color_upper": " ",
    "markdown_full": "[category_warehouse](https://github.com/oomlout/oomlout_oomp_current_version_messy/tree/main/parts/category_warehouse)<br>[](https://github.com/oomlout/oomlout_oomp_current_version_messy/tree/main/parts/category_warehouse)<br>[Category Warehouse](https://github.com/oomlout/oomlout_oomp_current_version_messy/tree/main/parts/category_warehouse)<br><br>",
    "markdown_short": "[category_warehouse](https://github.com/oomlout/oomlout_oomp_current_version_messy/tree/main/parts/category_warehouse)<br><br>"
}