{
    "classification": "category",
    "type": "mechanical",
    "size": "timing_belt",
    "color": "",
    "description_main": "",
    "description_extra": "tote",
    "manufacturer": "",
    "part_number": "",
    "from_yaml": false,
    "make_files": true,
    "filter": "",
    "part_number_exact": "",
    "description": "category_mechanical",
    "short_name": "Categorymechanical",
    "classification_upper": "CATEGORY",
    "classification_capital": "Category",
    "classification_first_letter": "c",
    "classification_first_letter_upper": "C",
    "type_upper": "MECHANICAL",
    "type_capital": "Mechanical",
    "type_first_letter": "m",
    "type_first_letter_upper": "M",
    "size_upper": "TIMING_BELT",
    "size_capital": "Timing Belt",
    "size_first_letter": "t",
    "size_first_letter_upper": "T",
    "color_upper": "",
    "color_capital": "",
    "color_first_letter": "",
    "color_first_letter_upper": "",
    "description_main_upper": "",
    "description_main_capital": "",
    "description_main_first_letter": "",
    "description_main_first_letter_upper": "",
    "description_extra_upper": "TOTE",
    "description_extra_capital": "Tote",
    "description_extra_first_letter": "t",
    "description_extra_first_letter_upper": "T",
    "manufacturer_upper": "",
    "manufacturer_capital": "",
    "manufacturer_first_letter": "",
    "manufacturer_first_letter_upper": "",
    "part_number_upper": "",
    "part_number_capital": "",
    "part_number_first_letter": "",
    "part_number_first_letter_upper": "",
    "id": "category_mechanical_timing_belt_tote",
    "id_no_class": "mechanical_timing_belt_tote",
    "id_no_type": "timing_belt_tote",
    "id_no_size": "tote",
    "oomp_key": "oomp_category_mechanical_timing_belt_tote",
    "link_github": "https://github.com/oomlout/oomlout_oomp_version_1_messy/tree/main/parts/category_mechanical_timing_belt_tote",
    "link_main": "https://github.com/oomlout/oomlout_oomp_version_1_messy/tree/main/parts/category_mechanical_timing_belt_tote",
    "link_redirect": "https://github.com/oomlout/oomlout_oomp_version_1_messy/tree/main/parts/category_mechanical_timing_belt_tote",
    "directory": "parts/category_mechanical_timing_belt_tote",
    "name": "Category Mechanical Timing Belt Tote",
    "name_no_class": "Mechanical Timing Belt Tote",
    "name_no_type": "Timing Belt Tote",
    "name_no_size": "Tote",
    "short_code": "",
    "short_code_upper": "",
    "distributors": [],
    "manufacturers": [],
    "md5": "ca2fa93a9c688b4041108fac401195e9",
    "md5_5": "ca2fa",
    "md5_5_upper": "CA2FA",
    "md5_6": "ca2fa9",
    "md5_6_upper": "CA2FA9",
    "md5_6_alpha": "7w04p",
    "md5_6_alpha_upper": "7W04P",
    "md5_10": "ca2fa93a9c",
    "md5_10_upper": "CA2FA93A9C",
    "oomp_word": "cherries cyclone sandal",
    "oomp_word_list": [
        "cherries",
        "cyclone",
        "sandal"
    ],
    "oomp_word_emoji": ":cherries: :cyclone: :sandal:",
    "oomp_word_emoji_list": [
        ":cherries:",
        ":cyclone:",
        ":sandal:"
    ],
    "size_only_numbers": "",
    "size_only_numbers_no_zeros": "",
    "description_only_numbers": "",
    "description_only_numbers_short": " ",
    "name_no_size_short": "Tote",
    "description_or_color": " ",
    "description_or_color_upper": " ",
    "markdown_full": "[category_mechanical_timing_belt_tote](none)<br>[](none)<br>[Category Mechanical Timing Belt Tote](none)<br><br>",
    "markdown_short": "[category_mechanical_timing_belt_tote](none)<br><br>"
}